OrchestratorAPI/__init__.py
OrchestratorAPI/api_client.py
OrchestratorAPI/api_response.py
OrchestratorAPI/configuration.py
OrchestratorAPI/exceptions.py
OrchestratorAPI/py.typed
OrchestratorAPI/rest.py
OrchestratorAPI/api/__init__.py
OrchestratorAPI/api/create_api.py
OrchestratorAPI/api/orchestrate_api.py
OrchestratorAPI/models/__init__.py
OrchestratorAPI/models/dummy.py
OrchestratorAPI/models/request_body.py
OrchestratorAPI/models/request_body_components_inner.py
OrchestratorAPI/models/request_body_components_inner_io_handles.py
OrchestratorAPI/models/request_body_components_inner_io_handles_input_inner.py
orchestratorapi-1.3.1.dist-info/METADATA
orchestratorapi-1.3.1.dist-info/WHEEL
orchestratorapi-1.3.1.dist-info/top_level.txt
orchestratorapi-1.3.1.dist-info/RECORD
