Metadata-Version: 2.4
Name: OrchestratorAPI
Version: 1.3.1
Summary: OrchestratorAPI
Home-page: 
Author: Luke Brown
Author-email: luke.brown@3adesign.co.uk
Keywords: OpenAPI,OpenAPI-Generator,OrchestratorAPI
Requires-Dist: urllib3<3.0.0,>=1.25.3
Requires-Dist: python-dateutil>=2.8.2
Requires-Dist: pydantic>=2
Requires-Dist: typing-extensions>=4.7.1
Dynamic: author
Dynamic: author-email
Dynamic: description
Dynamic: description-content-type
Dynamic: keywords
Dynamic: requires-dist
Dynamic: summary
